msfpatterns/__init__.py
msfpatterns/cli.py
msfpatterns-9.1.0.dist-info/METADATA
msfpatterns-9.1.0.dist-info/WHEEL
msfpatterns-9.1.0.dist-info/entry_points.txt
msfpatterns-9.1.0.dist-info/licenses/LICENCE
msfpatterns-9.1.0.dist-info/RECORD
