Metadata-Version: 2.4
Name: msfpatterns
Version: 9.1.0
Summary: Generate/find patterns for use in stack smashing alla pattern_{create,offset}.rb from Metasploit
Project-URL: Changelog, https://github.com/wrboyce/msfpatterns/blob/master/CHANGELOG.md
Project-URL: Homepage, https://github.com/wrboyce/msfpatterns
Project-URL: Issues, https://github.com/wrboyce/msfpatterns/issues
Project-URL: Repository, https://github.com/wrboyce/msfpatterns.git
Author-email: Will Boyce <me@willboyce.com>
License-Expression: BSD-3-Clause
License-File: LICENCE
Classifier: Programming Language :: Python :: 3 :: Only
Classifier: Programming Language :: Python :: 3.10
Classifier: Programming Language :: Python :: 3.11
Classifier: Programming Language :: Python :: 3.12
Classifier: Programming Language :: Python :: 3.13
Requires-Python: >=3.10
